igit/__init__.py
igit/__version__.py
igit/cli.py
igit/core/__init__.py
igit/core/commands.py
igit/core/config.py
igit/core/fs_ops.py
igit/core/git_ops.py
igit/core/ignore_files.py
igit/core/shell_ops.py
igit/interactive/__init__.py
igit/interactive/display.py
igit/interactive/interact.py
igit/tests/__init__.py
igit/tests/test_main.py
igit/tests/test_static.py
igit/tests/utils.py
igit-2020.12.5.dist-info/LICENSE.txt
igit-2020.12.5.dist-info/METADATA
igit-2020.12.5.dist-info/WHEEL
igit-2020.12.5.dist-info/entry_points.txt
igit-2020.12.5.dist-info/top_level.txt
igit-2020.12.5.dist-info/RECORD
