Metadata-Version: 2.1
Name: igit
Version: 2020.12.5
Summary: Interactive git and more
Home-page: https://github.com/kobibarhanin/igit
Author: kobi
Author-email: 
License: UNKNOWN
Platform: UNKNOWN
Classifier: Programming Language :: Python :: 3.7
Classifier: Programming Language :: Python :: 3.8
Classifier: Programming Language :: Python :: 3.9
Classifier: License :: OSI Approved :: MIT License
Classifier: Operating System :: OS Independent
Classifier: Development Status :: 4 - Beta
Requires-Python: >=3.7
Requires-Dist: astroid (==2.4.2)
Requires-Dist: attrs (==20.2.0)
Requires-Dist: blessed (==1.17.6)
Requires-Dist: certifi (==2020.6.20)
Requires-Dist: chardet (==3.0.4)
Requires-Dist: click (==7.1.2)
Requires-Dist: click-help-colors (==0.8)
Requires-Dist: gitdb (==4.0.5)
Requires-Dist: gitignore-parser (==0.0.8)
Requires-Dist: GitPython (==3.1.9)
Requires-Dist: idna (==2.10)
Requires-Dist: importlib-metadata (==2.0.0)
Requires-Dist: iniconfig (==1.1.1)
Requires-Dist: inquirer (==2.7.0)
Requires-Dist: invoke (==1.4.1)
Requires-Dist: isort (==5.6.4)
Requires-Dist: lazy-object-proxy (==1.4.3)
Requires-Dist: mccabe (==0.6.1)
Requires-Dist: packaging (==20.4)
Requires-Dist: pathlib2 (==2.3.5)
Requires-Dist: pluggy (==0.13.1)
Requires-Dist: prompt-toolkit (==1.0.14)
Requires-Dist: py (==1.9.0)
Requires-Dist: Pygments (==2.7.1)
Requires-Dist: PyInquirer (==1.0.3)
Requires-Dist: pylint (==2.6.0)
Requires-Dist: pyparsing (==2.4.7)
Requires-Dist: pytest (==6.1.1)
Requires-Dist: python-editor (==1.0.4)
Requires-Dist: readchar (==2.0.1)
Requires-Dist: regex (==2020.10.15)
Requires-Dist: requests (==2.24.0)
Requires-Dist: six (==1.15.0)
Requires-Dist: smmap (==3.0.4)
Requires-Dist: toml (==0.10.1)
Requires-Dist: typed-ast (==1.4.1)
Requires-Dist: urllib3 (==1.25.11)
Requires-Dist: wcwidth (==0.2.5)
Requires-Dist: wrapt (==1.12.1)
Requires-Dist: zipp (==3.3.1)
Requires-Dist: rich (==9.2.0)
